redo/__init__.py
redo/cmd.py
redo-2.0.2.dist-info/AUTHORS
redo-2.0.2.dist-info/METADATA
redo-2.0.2.dist-info/WHEEL
redo-2.0.2.dist-info/entry_points.txt
redo-2.0.2.dist-info/top_level.txt
redo-2.0.2.dist-info/RECORD
