Metadata-Version: 2.1
Name: redo
Version: 2.0.2
Summary: Utilities to retry Python callables.
Home-page: https://github.com/bhearsum/redo
Author: Ben Hearsum
Author-email: ben@hearsum.ca
License: UNKNOWN
Platform: UNKNOWN
